AUTHOR.txt
CHANGES.txt
LICENSE.txt
MANIFEST.in
README.txt
bootstrap.py
buildout.cfg
setup.cfg
setup.py
version.txt
src/rod/__init__.py
src/rod.recipe.mongodb.egg-info/PKG-INFO
src/rod.recipe.mongodb.egg-info/SOURCES.txt
src/rod.recipe.mongodb.egg-info/dependency_links.txt
src/rod.recipe.mongodb.egg-info/entry_points.txt
src/rod.recipe.mongodb.egg-info/namespace_packages.txt
src/rod.recipe.mongodb.egg-info/not-zip-safe
src/rod.recipe.mongodb.egg-info/requires.txt
src/rod.recipe.mongodb.egg-info/top_level.txt
src/rod/recipe/__init__.py
src/rod/recipe/mongodb/README.txt
src/rod/recipe/mongodb/__init__.py
src/rod/recipe/mongodb/tests/__init__.py
src/rod/recipe/mongodb/tests/test_doc.py