Metadata-Version: 1.0
Name: rod.recipe.mongodb
Version: 1.2.2
Summary: ZC Buildout recipe for setting up mongoDB.
Home-page: http://pypi.python.org/pypi/rod.recipe.mongodb
Author: Tobias Rodaebel
Author-email: tobias (dot) rodaebel (at) googlemail (dot) com
License: LGPL 3
Keywords: mongodb zc.buildout recipe
Platform: UNKNOWN
Classifier: Development Status :: 5 - Production/Stable
Classifier: Framework :: Buildout
Classifier: Intended Audience :: Developers
Classifier: License :: OSI Approved :: GNU Library or Lesser General Public License (LGPL)
Classifier: Topic :: Software Development :: Build Tools
Classifier: Topic :: Software Development :: Libraries :: Python Modules
